CMakeLists.txt
LICENSE
MANIFEST.in
README.md
pyproject.toml
setup.py
pyCollier/__info__.py
pyCollier/__init__.py
pyCollier/frontend.py
pyCollier.egg-info/PKG-INFO
pyCollier.egg-info/SOURCES.txt
pyCollier.egg-info/dependency_links.txt
pyCollier.egg-info/requires.txt
pyCollier.egg-info/top_level.txt
src/pyCollier.f90
tests/__init__.py
tests/test_Collier.py