Metadata-Version: 2.4
Name: pyCollier
Version: 0.3.3
Summary: access COLLIER loop functions via python
Home-page: 
Author: Henning Bahl, Johannes Braathen, Martin Gabelmann, Georg Weiglein
Author-email: 
License: MIT
Classifier: License :: OSI Approved :: MIT License
Classifier: Programming Language :: Python
Classifier: Programming Language :: Python :: 3
Classifier: Programming Language :: Python :: 3.6
Classifier: Programming Language :: Python :: 3.7
Classifier: Programming Language :: Python :: 3.8
Requires-Python: >=3.6, <4
License-File: LICENSE
Requires-Dist: numpy<2,>=1.13.0
Provides-Extra: docs
Provides-Extra: test
Provides-Extra: examples
Dynamic: author
Dynamic: classifier
Dynamic: description
Dynamic: description-content-type
Dynamic: license
Dynamic: license-file
Dynamic: provides-extra
Dynamic: requires-dist
Dynamic: requires-python
Dynamic: summary
